setup.py
hk2/__init__.py
hk2/annotations/__init__.py
hk2/annotations/contract.py
hk2/annotations/service.py
hk2/extensions/__init__.py
hk2/extensions/interfaces.py
hk2/extensions/utils.py
hk2/extensions/impl/__init__.py
hk2/extensions/impl/extension.py
hk2/extensions/impl/extension_point.py
hk2/extensions/impl/plugin_graph.py
hk2/extensions/impl/plugin_manager.py
hk2/extensions/impl/plugin_shadow.py
hk2/extensions/impl/declarative/__init__.py
hk2/extensions/impl/declarative/declarative_plugin_scanner.py
hk2/extensions/impl/declarative/plugin_desc_parser.py
hk2/injection/__init__.py
hk2/injection/activators.py
hk2/injection/bindings.py
hk2/injection/container.py
hk2/injection/exceptions.py
hk2/injection/inject.py
hk2/injection/injection_context.py
hk2/injection/injectors.py
hk2/injection/internal.py
hk2/injection/scopes.py
hk2/kernel/__init__.py
hk2/kernel/habitat.py
hk2/kernel/interfaces.py
hk2/kernel/module_scanner.py
hk2/kernel/utils.py
hk2/kernel/plugin_loaders/__init__.py
hk2/kernel/plugin_loaders/file_plugin_loader.py
hk2/kernel/plugin_loaders/sysmod_plugin_loader.py
hk2/types/__init__.py
hk2/types/annotations.py
hk2/types/enum.py
hk2/types/interface.py
hk2/utils/__init__.py
hk2/utils/func.py
hk2/utils/pathutil.py
hk2/utils/version.py
pyhk2.egg-info/PKG-INFO
pyhk2.egg-info/SOURCES.txt
pyhk2.egg-info/dependency_links.txt
pyhk2.egg-info/not-zip-safe
pyhk2.egg-info/top_level.txt