Metadata-Version: 1.0
Name: pyhk2
Version: 0.0.1
Summary: Hundred-Kilobyte Kernel library for dependency injection and service discovery
Home-page: https://github.com/mikhtonyuk/pyhk2
Author: Sergii Mikhtoniuk
Author-email: mikhtonyuk@gmail.com
License: MIT
Keywords: injection,ioc,container,plugin,discovery,service,contract,hk2,kernel
Platform: UNKNOWN
